CP3SlurmUtils/Configuration.py
CP3SlurmUtils/ConfigurationUtils.py
CP3SlurmUtils/Exceptions.py
CP3SlurmUtils/InteractiveQuestion.py
CP3SlurmUtils/Py2Py3Helpers.py
CP3SlurmUtils/SpellChecker.py
CP3SlurmUtils/SubmitUtils.py
CP3SlurmUtils/SubmitWorker.py
CP3SlurmUtils/__init__.py
CP3SlurmUtils/examples/config_example.py
CP3SlurmUtils/examples/config_template.py
CP3SlurmUtils-0.3.1.data/data/etc/CP3SlurmUtils/defaults.cfg.example
CP3SlurmUtils-0.3.1.data/scripts/slurm_resubmit
CP3SlurmUtils-0.3.1.data/scripts/slurm_submit
CP3SlurmUtils-0.3.1.dist-info/LICENSE
CP3SlurmUtils-0.3.1.dist-info/METADATA
CP3SlurmUtils-0.3.1.dist-info/WHEEL
CP3SlurmUtils-0.3.1.dist-info/top_level.txt
CP3SlurmUtils-0.3.1.dist-info/RECORD
