Metadata-Version: 2.1
Name: CP3SlurmUtils
Version: 0.3.1
Summary: Utilities package to submit jobs to SLURM using as input a python sbatch configuration file.
Home-page: https://gitlab.cern.ch/cp3-cms/CP3SlurmUtils
Author: Andres Tanasijczuk (Université catholique de Louvain)
Author-email: cp3-support@listes.uclouvain.be
License: GPL-3.0-or-later
Keywords: slurm
Platform: UNKNOWN
Classifier: Development Status :: 5 - Production/Stable
Classifier: Intended Audience :: Developers
Classifier: Intended Audience :: Science/Research
Classifier: Topic :: Scientific/Engineering
Classifier: Topic :: Scientific/Engineering :: Information Analysis
Classifier: Topic :: Scientific/Engineering :: Physics
Classifier: Topic :: Software Development :: Libraries :: Python Modules
Classifier: Topic :: System :: Distributed Computing
Classifier: License :: OSI Approved :: GNU General Public License v3 (GPLv3)
Classifier: Operating System :: OS Independent
Classifier: Programming Language :: Python :: 2
Classifier: Programming Language :: Python :: 2.7
Classifier: Programming Language :: Python :: 3
Classifier: Programming Language :: Python :: 3.6
Classifier: Programming Language :: Python :: 3.7
License-File: LICENSE
